smdbcq/__init__.py
smdbcq/__main__.py
smdbcq/nets.py
smdbcq/smdbcq.py
pytorch_smdbcq-0.0.1.dist-info/LICENSE
pytorch_smdbcq-0.0.1.dist-info/METADATA
pytorch_smdbcq-0.0.1.dist-info/WHEEL
pytorch_smdbcq-0.0.1.dist-info/top_level.txt
pytorch_smdbcq-0.0.1.dist-info/RECORD
