Metadata-Version: 2.1
Name: pytorch-smdbcq
Version: 0.0.1
Summary: PyTorch implementation of the semi-markov dBCQ RL model
Author-email: Walter Nelson <walterj.nelson@mail.utoronto.ca>
License: Creative Commons Legal Code        
Project-URL: Homepage, https://github.com/hamilton-health-sciences/smdbcq
Project-URL: Bug Tracker, https://github.com/hamilton-health-sciences/smdbcq/issues
Classifier: Programming Language :: Python :: 3
Classifier: Operating System :: OS Independent
Requires-Python: >=3.7
License-File: LICENSE
Requires-Dist: torch (>=1.9.0)
Requires-Dist: d3rlpy (==1.1.1)
